adafruit_displayio_ssd1305.py
adafruit_circuitpython_displayio_ssd1305-2.0.2.dist-info/licenses/LICENSE
adafruit_circuitpython_displayio_ssd1305-2.0.2.dist-info/METADATA
adafruit_circuitpython_displayio_ssd1305-2.0.2.dist-info/WHEEL
adafruit_circuitpython_displayio_ssd1305-2.0.2.dist-info/top_level.txt
adafruit_circuitpython_displayio_ssd1305-2.0.2.dist-info/RECORD
