Metadata-Version: 2.4
Name: adafruit-circuitpython-displayio-ssd1305
Version: 2.0.2
Summary: DisplayIO driver for SSD1305 monochrome displays
Author-email: Adafruit Industries <circuitpython@adafruit.com>
License: MIT
Project-URL: Homepage, https://github.com/adafruit/Adafruit_CircuitPython_DisplayIO_SSD1305
Keywords: adafruit,blinka,circuitpython,micropython,displayio_ssd1305,displayio,ssd1305,oled
Classifier: Intended Audience :: Developers
Classifier: Topic :: Software Development :: Libraries
Classifier: Topic :: Software Development :: Embedded Systems
Classifier: Topic :: System :: Hardware
Classifier: License :: OSI Approved :: MIT License
Classifier: Programming Language :: Python :: 3
License-File: LICENSE
Requires-Dist: Adafruit-Blinka
Provides-Extra: optional
Dynamic: license-file
